bbb_selenium_exporter/__init__.py
bbb_selenium_exporter/__main__.py
bbb_selenium_exporter/bbb.py
bbb_selenium_exporter/collect.py
bbb_selenium_exporter/server.py
bbb_selenium_exporter/assets/red.pdf
bbb_selenium_exporter-0.1.1.dist-info/LICENSE
bbb_selenium_exporter-0.1.1.dist-info/METADATA
bbb_selenium_exporter-0.1.1.dist-info/WHEEL
bbb_selenium_exporter-0.1.1.dist-info/entry_points.txt
bbb_selenium_exporter-0.1.1.dist-info/top_level.txt
bbb_selenium_exporter-0.1.1.dist-info/RECORD
